recordmaster/__init__.py
recordmaster/_api.py
recordmaster/_config.py
recordmaster/_data.py
recordmaster/_get_records.py
recordmaster/_match_records.py
recordmaster/_sync_records.py
recordmaster/main.py
inwx_dns_recordmaster-1.0.2.dist-info/METADATA
inwx_dns_recordmaster-1.0.2.dist-info/WHEEL
inwx_dns_recordmaster-1.0.2.dist-info/entry_points.txt
inwx_dns_recordmaster-1.0.2.dist-info/licenses/LICENSE.txt
inwx_dns_recordmaster-1.0.2.dist-info/licenses/LICENSES/Apache-2.0.txt
inwx_dns_recordmaster-1.0.2.dist-info/licenses/LICENSES/CC-BY-4.0.txt
inwx_dns_recordmaster-1.0.2.dist-info/licenses/LICENSES/CC0-1.0.txt
inwx_dns_recordmaster-1.0.2.dist-info/licenses/LICENSES/GPL-3.0-only.txt
inwx_dns_recordmaster-1.0.2.dist-info/RECORD
