Metadata-Version: 2.4
Name: inwx-dns-recordmaster
Version: 1.0.2
Summary: Manage DNS nameserver records of INWX domains via YAML files and API requests. Lightweight, version-control ready
License: GPL-3.0-only
License-File: LICENSE.txt
License-File: LICENSES/Apache-2.0.txt
License-File: LICENSES/CC-BY-4.0.txt
License-File: LICENSES/CC0-1.0.txt
License-File: LICENSES/GPL-3.0-only.txt
Keywords: inwx,dns,nameserver,automation,configuration-management
Author: Max Mehl
Author-email: mail@mehl.mx
Requires-Python: >=3.10,<4.0
Classifier: Development Status :: 5 - Production/Stable
Classifier: Environment :: Console
Classifier: Intended Audience :: Developers
Classifier: Intended Audience :: System Administrators
Classifier: License :: OSI Approved :: GNU General Public License v3 (GPLv3)
Classifier: Programming Language :: Python :: 3
Classifier: Programming Language :: Python :: 3.10
Classifier: Programming Language :: Python :: 3.11
Classifier: Programming Language :: Python :: 3.12
Classifier: Programming Language :: Python :: 3.13
Classifier: Programming Language :: Python :: 3.14
Classifier: Topic :: Internet :: Name Service (DNS)
Classifier: Topic :: Software Development :: Version Control :: Git
Classifier: Topic :: System :: Systems Administration
Requires-Dist: inwx-domrobot (>=3.2.0,<4.0.0)
Requires-Dist: jsonschema (>=4.25.1,<5.0.0)
Requires-Dist: platformdirs (>=4.5.0,<5.0.0)
Requires-Dist: pyyaml (>=6.0.3,<7.0.0)
Requires-Dist: toml (>=0.10.2,<0.11.0)
Project-URL: Repository, https://github.com/mxmehl/inwx-dns-recordmaster
